{
  "id": "intro-1-linkedin",
  "platform": "LinkedIn",
  "scheduled_at": "2026-05-18T09:00:00-04:00",
  "status": "draft",
  "carousel_ref": "intro-1-who-is-glv-2026-05-18-v4",
  "caption": "GLV exists because local businesses in Northern Ontario keep losing leads they don't even know about.\n\nWrong GBP categories. No local content. Invisible on Maps. None of it is hard to fix. It's just what gets missed when no one's looking at the whole system.\n\nWe handle SEO, websites, email, paid ads, and AI integration for small and mid-size businesses across Northern Ontario and Canada. One team, one strategy.\n\nComment AUDIT below and I'll DM you a free 15-min Google Business Profile audit. Exactly why you're not showing up and what to fix first.\n\nWhat's the biggest marketing challenge you're dealing with right now?",
  "hashtags": [
    "#LocalSEO",
    "#SmallBusinessMarketing",
    "#NorthernOntario",
    "#DigitalMarketing",
    "#SaultSteMarie"
  ],
  "audio_brief": null,
  "geotag": null,
  "blotato_job_id": null,
  "category": "Marketing",
  "first_comment": "Full intro in the carousel above. Comment AUDIT for a free GBP audit or visit glvmarketing.ca",
  "manychat_keyword_triggers": ["AUDIT"],
  "manychat_dm_template_id": null
}
